MANIFEST.in
README.md
requirements.txt
setup.py
version.py
interactive_session.egg-info/PKG-INFO
interactive_session.egg-info/SOURCES.txt
interactive_session.egg-info/dependency_links.txt
interactive_session.egg-info/not-zip-safe
interactive_session.egg-info/requires.txt
interactive_session.egg-info/top_level.txt
src/main.cxx
src/session.cxx
src/session.hpp
src/test_session.cxx
tests/__init__.py
tests/test.py