Metadata-Version: 2.1
Name: interactive-session
Version: 0.0.3
Summary: A shell session project using pybind11
Home-page: https://github.com/bochen0909/interactive-session
Author: Bo Chen
Author-email: bochen0909@gmail.com
Requires-Python: >=3.8
Requires-Dist: setuptools==69.0.3
Requires-Dist: wheel==0.42.0
Requires-Dist: pybind11==2.11.1
Provides-Extra: test
Requires-Dist: pytest; extra == "test"
